{"metadata":{"type":"page"},"title":"TS-5 — Command Surface","url":"https://www.notion.so/35f010d46a70815eae12ffb05cf14a9a","text":"<content>\nTS-5 — COMMAND SURFACE. Maps to FR-TRUST-3, FR-TRUST-5, FR-METRICS-1..3, FR-MANIFEST-5, DD-130 carry.\n/coherence:trust dispatcher (src/commands/trust.ts): subcommands via flag inspection: --status (default), sync, --promote, --prune-stale.\n--status: read personal ledger + team aggregate, render 5-section Markdown: (a) current state (promoted_at, auto_land_kinds, hint_emitted); (b) top 5 highest personal; (c) top 5 lowest personal; (d) team summary (active developer count, contested-section count); (e) promote eligibility (3 conditions met/pending).\nsync: invokes teamAggregate.writeOwnFile(personalLedger). Prints confirmation with file path + timestamp.\n--promote --auto-land <kinds>: checks eligibility; if conditions met, atomically writes promoted_at + auto_land_kinds to personal ledger. --auto-land omitted defaults to ['annotate'] (DD-146).\n--prune-stale: invokes listStaleFiles then pruneStale after --yes. Prints count + paths.\nPerf bound (NFR-PERF-N6 pass3): --status < 200 ms p95.\n/coherence:metrics renderer (src/commands/metrics.ts) — 5 Markdown sections (FR-METRICS-1):\n(1) Summary — count accept/revert/edit/discard all-time + last 30 days. 2-col table.\n(2) Top drifting sections — group coherence-log.md by sectionRef; count applications; sort desc; top 10. Contested marked ⚠ (FR-LEDGER-4 pass3).\n(3) Trust scores — sort by score; top 10 highest with personal+team side-by-side; top 10 lowest. Empty: 'No trust data yet — run more sessions to accumulate metrics.'\n(4) Cost trend — bucket cost-ledger.json by day, last 30 days. Unicode sparkline ▁▂▃▄▅▆▇█. Linear scale. Empty: '< 3 sessions — no trend yet.'\n(5) Revert hotspots — sections with ≥ 5 events; revert rate = reverts/(accepts+reverts+edits) per FR-METRICS-3. Filter > threshold (default 0.20). Sort desc.\nFlags: --since <ISO> (reuses src/util/dateFilter.ts); --out <path> (DD-128 sandbox NFR-PATH-SANDBOX); --revert-threshold <pct> integer 0-100 default 20.\nPerf bound (NFR-PERF-N6): < 200 ms p95.\nSentinel dispatch (DD-130 carry from v0.4): scripts/generate-command-stubs.mjs auto-generates commands/trust.md and commands/metrics.md at build time. Each stub contains <!-- coherence-command: <name> --> sentinel + brief description. userPromptSubmit detects sentinel; commandDispatch routes to JS handler.\nplugin.json (FR-MANIFEST-5): add slashCommands {coherence:trust} and {coherence:metrics}. Version → 1.0.0. assertVersionSync verifies package.json + plugin.json + PLUGIN_VERSION lockstep.\nAudit#14: --revert-threshold PERCENT integer [0,100] default 20. rate*100 >= threshold. Invalid rejected.\nAudit minor: dispatch — argv[0]==='sync' → sync; else --promote → promote; else --prune-stale → prune; else --status default. Sparkline edge cases: all-zero → flat ▁; single point → █; max==min → ▄. --out same Markdown.\n</content>"}
